MANIFEST.in
README.md
build.py
requirements.txt
setup.py
sniffing_io.egg-info/PKG-INFO
sniffing_io.egg-info/SOURCES.txt
sniffing_io.egg-info/dependency_links.txt
sniffing_io.egg-info/requires.txt
sniffing_io.egg-info/top_level.txt
sniffingio/__init__.py
sniffingio/callbacks.py
sniffingio/data.py
sniffingio/filters.py
sniffingio/listener.py
sniffingio/sniff.py