Metadata-Version: 2.1
Name: sniffing-io
Version: 0.3.2
Summary: A simple package for packet sniffing, with static/dynamic filtering options, real-time reaction, I/O operations and more.
Home-page: https://github.com/Shahaf-F-S/sniffing-io
Author: Shahaf Frank-Shapir
Author-email: shahaffrs@gmail.com
License: MIT
Classifier: Intended Audience :: Developers
Classifier: License :: OSI Approved :: MIT License
Classifier: Programming Language :: Python
Classifier: Programming Language :: Python :: 3
Classifier: Programming Language :: Python :: 3.8
Classifier: Programming Language :: Python :: 3.9
Classifier: Programming Language :: Python :: 3.10
Classifier: Programming Language :: Python :: 3.11
Classifier: Operating System :: OS Independent
Requires-Dist: scapy
Provides-Extra: dev
